bands.py
bands-0.1.3.dist-info/METADATA
bands-0.1.3.dist-info/RECORD
bands-0.1.3.dist-info/WHEEL
bands-0.1.3.dist-info/top_level.txt
