Metadata-Version: 2.1
Name: bands
Version: 0.1.3
Summary: Another message passing library.
Home-page: https://github.com/danielbradham/bands.git
Author: Dan Bradham
Author-email: danielbradham@gmail.com
License: MIT
Platform: UNKNOWN
Classifier: Development Status :: 3 - Alpha
Classifier: Intended Audience :: Developers
Classifier: License :: OSI Approved :: MIT License
Classifier: Natural Language :: English
Classifier: Operating System :: OS Independent
Classifier: Programming Language :: Python
Classifier: Programming Language :: Python :: 2
Classifier: Programming Language :: Python :: 3
Classifier: Topic :: Software Development :: Libraries :: Python Modules
